{
	"components": {
		"examples": {},
		"headers": {},
		"parameters": {},
		"requestBodies": {},
		"responses": {},
		"schemas": {
			"RecordType": {
				"enum": [
					"mutu",
					"teknis"
				],
				"type": "string"
			},
			"RecordDTO": {
				"properties": {
					"id": {
						"type": "string"
					},
					"type": {
						"$ref": "#/components/schemas/RecordType"
					},
					"pic": {
						"type": "string"
					},
					"area": {
						"type": "string"
					},
					"title": {
						"type": "string"
					},
					"year": {
						"type": "number",
						"format": "double"
					},
					"resensi": {
						"type": "string",
						"format": "date-time"
					},
					"file_path": {
						"type": "string"
					}
				},
				"required": [
					"type",
					"title",
					"year",
					"resensi"
				],
				"type": "object",
				"additionalProperties": false
			},
			"SdmStatus": {
				"enum": [
					"menikah",
					"lajang",
					"pelajar/mahasiswa",
					"pekerja"
				],
				"type": "string"
			},
			"SdmEducationDTO": {
				"properties": {
					"id": {
						"type": "string"
					},
					"instance_name": {
						"type": "string"
					},
					"major_name": {
						"type": "string"
					},
					"level": {
						"type": "string"
					}
				},
				"required": [
					"instance_name",
					"major_name",
					"level"
				],
				"type": "object",
				"additionalProperties": false
			},
			"SdmWorkExperienceDTO": {
				"properties": {
					"id": {
						"type": "string"
					},
					"company_name": {
						"type": "string"
					},
					"position": {
						"type": "string"
					},
					"year": {
						"type": "number",
						"format": "double"
					}
				},
				"required": [
					"company_name",
					"position",
					"year"
				],
				"type": "object",
				"additionalProperties": false
			},
			"SdmFunctionalDTO": {
				"properties": {
					"id": {
						"type": "string"
					},
					"schema": {
						"type": "string"
					},
					"scope": {
						"type": "string"
					},
					"position": {
						"type": "string"
					}
				},
				"required": [
					"schema",
					"scope",
					"position"
				],
				"type": "object",
				"additionalProperties": false
			},
			"SdmDTO": {
				"properties": {
					"id": {
						"type": "string"
					},
					"name": {
						"type": "string"
					},
					"email": {
						"type": "string"
					},
					"phone": {
						"type": "string"
					},
					"address": {
						"type": "string"
					},
					"born_address": {
						"type": "string"
					},
					"born_date": {
						"type": "string",
						"format": "date-time"
					},
					"status": {
						"$ref": "#/components/schemas/SdmStatus"
					},
					"title": {
						"type": "string"
					},
					"educations": {
						"items": {
							"$ref": "#/components/schemas/SdmEducationDTO"
						},
						"type": "array"
					},
					"work_experiences": {
						"items": {
							"$ref": "#/components/schemas/SdmWorkExperienceDTO"
						},
						"type": "array"
					},
					"functionals": {
						"items": {
							"$ref": "#/components/schemas/SdmFunctionalDTO"
						},
						"type": "array"
					}
				},
				"required": [
					"name",
					"email",
					"phone",
					"address",
					"born_address",
					"born_date",
					"status"
				],
				"type": "object",
				"additionalProperties": false
			}
		},
		"securitySchemes": {}
	},
	"info": {
		"title": ""
	},
	"openapi": "3.0.0",
	"paths": {
		"/files/uploadFile": {
			"post": {
				"operationId": "UploadFile",
				"responses": {
					"200": {
						"description": "Ok",
						"content": {
							"application/json": {
								"schema": {}
							}
						}
					}
				},
				"security": [],
				"parameters": [],
				"requestBody": {
					"required": true,
					"content": {
						"multipart/form-data": {
							"schema": {
								"type": "object",
								"properties": {
									"file": {
										"type": "string",
										"format": "binary"
									},
									"fileType": {
										"type": "string"
									}
								},
								"required": [
									"file",
									"fileType"
								]
							}
						}
					}
				}
			}
		},
		"/api/records": {
			"post": {
				"operationId": "Create",
				"responses": {
					"200": {
						"description": "Ok",
						"content": {
							"application/json": {
								"schema": {}
							}
						}
					}
				},
				"tags": [
					"Record Services"
				],
				"security": [],
				"parameters": [],
				"requestBody": {
					"required": true,
					"content": {
						"application/json": {
							"schema": {
								"$ref": "#/components/schemas/RecordDTO"
							}
						}
					}
				}
			},
			"get": {
				"operationId": "Index",
				"responses": {
					"200": {
						"description": "Ok",
						"content": {
							"application/json": {
								"schema": {}
							}
						}
					}
				},
				"tags": [
					"Record Services"
				],
				"security": [],
				"parameters": [
					{
						"in": "query",
						"name": "page",
						"required": true,
						"schema": {
							"format": "double",
							"type": "number"
						}
					},
					{
						"in": "query",
						"name": "limit",
						"required": true,
						"schema": {
							"format": "double",
							"type": "number"
						}
					}
				]
			}
		},
		"/api/records/{id}": {
			"put": {
				"operationId": "Update",
				"responses": {
					"200": {
						"description": "Ok",
						"content": {
							"application/json": {
								"schema": {}
							}
						}
					}
				},
				"tags": [
					"Record Services"
				],
				"security": [],
				"parameters": [
					{
						"in": "path",
						"name": "id",
						"required": true,
						"schema": {
							"type": "string"
						}
					}
				],
				"requestBody": {
					"required": true,
					"content": {
						"application/json": {
							"schema": {
								"$ref": "#/components/schemas/RecordDTO"
							}
						}
					}
				}
			},
			"delete": {
				"operationId": "Delete",
				"responses": {
					"200": {
						"description": "Ok",
						"content": {
							"application/json": {
								"schema": {}
							}
						}
					}
				},
				"tags": [
					"Record Services"
				],
				"security": [],
				"parameters": [
					{
						"in": "path",
						"name": "id",
						"required": true,
						"schema": {
							"type": "string"
						}
					}
				]
			},
			"get": {
				"operationId": "Show",
				"responses": {
					"200": {
						"description": "Ok",
						"content": {
							"application/json": {
								"schema": {}
							}
						}
					}
				},
				"tags": [
					"Record Services"
				],
				"security": [],
				"parameters": [
					{
						"in": "path",
						"name": "id",
						"required": true,
						"schema": {
							"type": "string"
						}
					}
				]
			}
		},
		"/api/sdm": {
			"post": {
				"operationId": "Create",
				"responses": {
					"200": {
						"description": "Ok",
						"content": {
							"application/json": {
								"schema": {}
							}
						}
					}
				},
				"tags": [
					"Sdm Services"
				],
				"security": [],
				"parameters": [],
				"requestBody": {
					"required": true,
					"content": {
						"application/json": {
							"schema": {
								"$ref": "#/components/schemas/SdmDTO"
							}
						}
					}
				}
			},
			"get": {
				"operationId": "Index",
				"responses": {
					"200": {
						"description": "Ok",
						"content": {
							"application/json": {
								"schema": {}
							}
						}
					}
				},
				"tags": [
					"Sdm Services"
				],
				"security": [],
				"parameters": [
					{
						"in": "query",
						"name": "page",
						"required": true,
						"schema": {
							"format": "double",
							"type": "number"
						}
					},
					{
						"in": "query",
						"name": "limit",
						"required": true,
						"schema": {
							"format": "double",
							"type": "number"
						}
					}
				]
			}
		},
		"/api/sdm/{id}": {
			"put": {
				"operationId": "Update",
				"responses": {
					"200": {
						"description": "Ok",
						"content": {
							"application/json": {
								"schema": {}
							}
						}
					}
				},
				"tags": [
					"Sdm Services"
				],
				"security": [],
				"parameters": [
					{
						"in": "path",
						"name": "id",
						"required": true,
						"schema": {
							"type": "string"
						}
					}
				],
				"requestBody": {
					"required": true,
					"content": {
						"application/json": {
							"schema": {
								"$ref": "#/components/schemas/SdmDTO"
							}
						}
					}
				}
			},
			"delete": {
				"operationId": "Delete",
				"responses": {
					"200": {
						"description": "Ok",
						"content": {
							"application/json": {
								"schema": {}
							}
						}
					}
				},
				"tags": [
					"Sdm Services"
				],
				"security": [],
				"parameters": [
					{
						"in": "path",
						"name": "id",
						"required": true,
						"schema": {
							"type": "string"
						}
					}
				]
			},
			"get": {
				"operationId": "Show",
				"responses": {
					"200": {
						"description": "Ok",
						"content": {
							"application/json": {
								"schema": {}
							}
						}
					}
				},
				"tags": [
					"Sdm Services"
				],
				"security": [],
				"parameters": [
					{
						"in": "path",
						"name": "id",
						"required": true,
						"schema": {
							"type": "string"
						}
					}
				]
			}
		}
	},
	"servers": [
		{
			"url": "/"
		}
	]
}